scrapy_util/__init__.py
scrapy_util/logger.py
scrapy_util/spider_util.py
scrapy_util/utils.py
scrapy_util/version.py
scrapy_util/extensions/__init__.py
scrapy_util/extensions/localtime_core_stats.py
scrapy_util/extensions/show_duration_extension.py
scrapy_util/extensions/stats_collector_extension.py
scrapy_util/items/__init__.py
scrapy_util/items/mongo_item.py
scrapy_util/items/trick_item.py
scrapy_util/middlewares/__init__.py
scrapy_util/middlewares/dont_request_downloader_middleware.py
scrapy_util/pipelines/__init__.py
scrapy_util/pipelines/mongo_pipeline.py
scrapy_util/spiders/__init__.py
scrapy_util/spiders/list_next_request_spider.py
scrapy_util/spiders/list_spider.py
scrapy_util/spiders/script_spider.py
tests/__init__.py
tests/test_hello.py
scrapy_util-1.0.3.dist-info/METADATA
scrapy_util-1.0.3.dist-info/WHEEL
scrapy_util-1.0.3.dist-info/top_level.txt
scrapy_util-1.0.3.dist-info/zip-safe
scrapy_util-1.0.3.dist-info/RECORD
