Metadata-Version: 2.1
Name: scrapy-util
Version: 1.0.3
Summary: scrapy util
Home-page: https://github.com/mouday/scrapy-util
Author: Peng Shiyu
Author-email: pengshiyuyx@gmail.com
License: MIT
Keywords: spider,admin
Platform: UNKNOWN
Classifier: Programming Language :: Python :: 3
Classifier: Programming Language :: Python :: 3.6
Requires-Dist: six
Requires-Dist: md5util
Requires-Dist: pymongo
Requires-Dist: requests
Requires-Dist: scrapy
Requires-Dist: mo-cache
